vision_agents/plugins/gemini/__init__.py
vision_agents/plugins/gemini/events.py
vision_agents/plugins/gemini/file_search.py
vision_agents/plugins/gemini/gemini_llm.py
vision_agents/plugins/gemini/gemini_realtime.py
vision_agents/plugins/gemini/tools.py
vision_agents_plugins_gemini-0.2.10.dist-info/METADATA
vision_agents_plugins_gemini-0.2.10.dist-info/WHEEL
vision_agents_plugins_gemini-0.2.10.dist-info/RECORD
