Metadata-Version: 2.4
Name: vision-agents-plugins-gemini
Version: 0.2.10
Summary: Google Gemini LLM integration for Vision Agents
Project-URL: Documentation, https://visionagents.ai/
Project-URL: Website, https://visionagents.ai/
Project-URL: Source, https://github.com/GetStream/Vision-Agents
License-Expression: MIT
Keywords: AI,LLM,agents,gemini,google,voice agents
Requires-Python: >=3.10
Requires-Dist: google-genai>=1.55.0
Requires-Dist: numpy>=2.2.6
Requires-Dist: vision-agents
